CHANGES.rst
LICENSE
MANIFEST.in
setup.cfg
setup.py
jlle/__init__.py
jlle.egg-info/PKG-INFO
jlle.egg-info/SOURCES.txt
jlle.egg-info/dependency_links.txt
jlle.egg-info/entry_points.txt
jlle.egg-info/namespace_packages.txt
jlle.egg-info/not-zip-safe
jlle.egg-info/requires.txt
jlle.egg-info/top_level.txt
jlle/releaser/__init__.py
jlle/releaser/git.py
jlle/releaser/hg.py
jlle/releaser/pypi.py
jlle/releaser/release.py
jlle/releaser/utils.py
jlle/releaser/vcs.py
jlle/scaffold/__init__.py
jlle/scaffold/main.py
jlle/scaffold/licenses/Apache
jlle/scaffold/licenses/GPLv2
jlle/scaffold/licenses/GPLv3
jlle/scaffold/licenses/MIT
jlle/scaffold/licenses/Mozilla
jlle/scaffold/templates/.coveragerc
jlle/scaffold/templates/.gitignore
jlle/scaffold/templates/.travis.yml
jlle/scaffold/templates/CHANGES.rst
jlle/scaffold/templates/MANIFEST.in
jlle/scaffold/templates/README.rst
jlle/scaffold/templates/requirements.txt
jlle/scaffold/templates/setup.py
jlle/scaffold/templates/termite.yaml
jlle/scaffold/templates/tox.ini
jlle/scaffold/templates/+project+/__init__.py
jlle/scaffold/templates/docs/Makefile
jlle/scaffold/templates/docs/source/conf.py
jlle/scaffold/templates/docs/source/index.rst
jlle/scaffold/templates/docs/source/intro.rst
jlle/scaffold/templates/docs/source/_templates/links.html
jlle/scaffold/templates/tests/+project+_test.py