Metadata-Version: 1.1
Name: jlle
Version: 0.1.4
Summary: Utils to automate my process
Home-page:  https://github.com/jlesquembre/jlle
Author: José Luis Lafuente
Author-email: jlesquembre@gmail.com
License: GNU General Public License v3 (GPLv3)
Keywords: automation
Platform: UNKNOWN
Classifier: Development Status :: 3 - Alpha
Classifier: Topic :: Utilities
Classifier: Intended Audience :: Developers
Classifier: License :: OSI Approved :: GNU General Public License v3 (GPLv3)
Classifier: Operating System :: OS Independent
Classifier: Programming Language :: Python
Classifier: Programming Language :: Python :: 3.3
